{"EDITOR_STATE":{"allProjectFiles":{"bb3ac2dc-b16b-41a6-9d2e-05b6acfbf982":{"id":"bb3ac2dc-b16b-41a6-9d2e-05b6acfbf982","parent":null,"name":"FindChild","type":"DIRECTORY","isDirectory":true,"children":["a2f77a2a-1549-4c7f-9b2e-d30cd5ebcadc"],"isRemovable":false,"filePath":"FindChild"},"a2f77a2a-1549-4c7f-9b2e-d30cd5ebcadc":{"id":"a2f77a2a-1549-4c7f-9b2e-d30cd5ebcadc","parent":"bb3ac2dc-b16b-41a6-9d2e-05b6acfbf982","name":"lambda.js","type":"LAMBDA_FILE","isDirectory":false,"children":[],"isRemovable":true,"filePath":"FindChild/lambda.js","code":"let AWS = require('aws-sdk');\nconst ddb = new AWS.DynamoDB.DocumentClient();\nconst sns = new AWS.SNS();\nexports.handler = function (event, context, callback) {\n\n\tlet childrenid = Number(event['childrenid']);\n\tlet receiver;\n\tlet sender;\n\tlet message;\n\n\tconsole.log(childrenid);\n\n\tddb.get({\n\t\tTableName: 'children',\n\t\tKey: { 'id': childrenid }\n\t}, function (err, data) {\n\t\tif (err) {\n\t\t\tconsole.log(err);\n\t\t} else {\n\t\t\treceiver = data.Item['phone'];\n\t\t\tsender = 'AWS Lost Children';\n\t\t\tmessage = 'Your children is now with me';\n\t\t}\n\t});\n\n\tconsole.log(receiver)\n\tconsole.log(sender)\n\tconsole.log(message)\n\n\n\tconsole.log(\"Sending message\", message, \"to receiver\", receiver);\n\n\tsns.publish({\n\t\tMessage: message,\n\t\tMessageAttributes: {\n\t\t\t'AWS.SNS.SMS.SMSType': {\n\t\t\t\tDataType: 'String',\n\t\t\t\tStringValue: 'Promotional'\n\t\t\t},\n\t\t\t'AWS.SNS.SMS.SenderID': {\n\t\t\t\tDataType: 'String',\n\t\t\t\tStringValue: sender\n\t\t\t},\n\t\t},\n\t\tPhoneNumber: receiver\n\t}).promise()\n\t\t.then(data => {\n\t\t\tconsole.log(\"Sent message to\", receiver);\n\t\t\tcallback(null, data);\n\t\t})\n\t\t.catch(err => {\n\t\t\tconsole.log(\"Sending failed\", err);\n\t\t\tcallback(err);\n\t\t});\n}","triggers":[{"resourceName":"apigeuWest1FindChildsendSMSpost","config":{}}],"config":{"memory":128,"timeout":60,"runtime":"nodejs8.10"},"version":122,"syncVersion":52,"references":[],"testCases":{"d1c4c57a-da26-47f8-91e5-1e5516eb3914":{"id":"d1c4c57a-da26-47f8-91e5-1e5516eb3914","name":"teste","functionId":"a2f77a2a-1549-4c7f-9b2e-d30cd5ebcadc","event":"{\n    \"childrenid\": \"1234\"\n}"}}}},"rootNode":"bb3ac2dc-b16b-41a6-9d2e-05b6acfbf982","openFiles":["a2f77a2a-1549-4c7f-9b2e-d30cd5ebcadc"],"currentFileId":"a2f77a2a-1549-4c7f-9b2e-d30cd5ebcadc","resources":{"apigeuWest1FindChildsendSMSpost":{"name":"apigeuWest1FindChildsendSMSpost","type":"API_GATEWAY","config":{"selectedRegion":"eu-west-1","apiMode":0,"apiName":"FindChild","endpointType":"EDGE","resourceMode":0,"resourceName":"sendSMS","resourcePath":"/sendSMS","restMethod":"POST","proxyIntegration":false,"enableCORS":false,"stageMode":0,"stageName":"Prod"},"globallyEditable":true},"snsDirectSMSResource":{"name":"snsDirectSMSResource","type":"SNS","config":{"snsType":1,"numbers":["@{receiver}"]},"globallyEditable":false},"ddbchildren":{"name":"ddbchildren","type":"DynamoDB","config":{"mode":1,"operation":"get","table":{"arn":"arn:aws:dynamodb:eu-west-1:055219503923:table/children","name":"children","partitionKey":"id","partitionKeyType":"N","hasSortKey":false,"sortKey":"","sortKeyType":"S","mode":1},"parameters":{"Key":{"id":"@{childrenid}"},"Item":{},"ExpressionAttributeValues":{}},"validator":{"validatableFields":{},"validity":true},"valid":true},"globallyEditable":false}},"envVariables":[{"lambdaId":"all","varKey":"SIGMA_AWS_ACC_ID","varValue":null,"shouldPersist":false,"editable":false}],"packageJSON":{"dependencies":{"aws-sdk":{"name":"aws-sdk","version":"2.176.0","notRemovable":true}}},"lambdaId":"a2f77a2a-1549-4c7f-9b2e-d30cd5ebcadc","additionalFiles":[]},"PROJECT_META":{"projectName":"FindChild","projectDescription":"","projectVersion":"1.0.0","projectRegion":"eu-west-1","repoName":"FindChild","repoUrl":"https://github.com/johker1/FindChild","lastSave":1531493836948}}